breeze_historical/__init__.py
breeze_historical/breeze_auth.py
breeze_historical/client.py
breeze_historical/exceptions.py
breeze_historical/symbol_map.json
breeze_historical-0.1.3.dist-info/METADATA
breeze_historical-0.1.3.dist-info/WHEEL
breeze_historical-0.1.3.dist-info/top_level.txt
breeze_historical-0.1.3.dist-info/RECORD
