Metadata-Version: 2.4
Name: breeze-historical
Version: 0.1.3
Summary: A library for fetching and caching historical market data from Breeze API using DynamoDB
Home-page: https://github.com/yourusername/breeze-historical
Author: Your Name
Author-email: Kunal Agarwal <kunal.95a@gmail.com>
Project-URL: Homepage, https://github.com/yourusername/breeze-historical
Classifier: Programming Language :: Python :: 3
Classifier: License :: OSI Approved :: MIT License
Classifier: Operating System :: OS Independent
Requires-Python: >=3.7
Dynamic: author
Dynamic: home-page
Dynamic: requires-python
